{
  "region_name": "South Korea - Seoul",
  "google_module": {
    "base_lat": 37.5665,
    "base_lon": 126.978,
    "lang_params": "hl=ko&gl=KR",
    "valid_url_suffix": "co.kr"
  },
  "trust_module": {
    "white_urls": [
      "https://www.snu.ac.kr/",
      "https://www.kbstar.com/",
      "https://www.yonhapnewstv.co.kr/news/MYH20260629204141Ffj",
      "https://www.yonhapnewstv.co.kr/news/AKR202606300301231Xh",
      "https://www.yonhapnewstv.co.kr/news/MYH20260629224659P34",
      "https://www.yonhapnewstv.co.kr/news/MYH20260630004523jlp",
      "https://www.coupang.com/",
      "https://www.daum.net/",
      "https://www.naver.com/",
      "https://www.korea.kr/",
      "https://www.yonhapnewstv.co.kr/news/AKR20260630040252kGw",
      "https://www.hometax.go.kr/",
      "https://www.kakao.com/"
    ],
    "static_urls": [
      "https://www.korea.kr/",
      "https://www.hometax.go.kr/",
      "https://www.snu.ac.kr/",
      "https://www.kbstar.com/",
      "https://www.naver.com/",
      "https://www.daum.net/",
      "https://www.coupang.com/",
      "https://www.kakao.com/"
    ]
  }
}